kingdom_core/__init__.py
kingdom_core/database/__init__.py
kingdom_core/database/orm.py
kingdom_core/utils/__init__.py
kingdom_core/utils/files.py
kingdom_core-0.2.0.dist-info/LICENSE
kingdom_core-0.2.0.dist-info/METADATA
kingdom_core-0.2.0.dist-info/WHEEL
kingdom_core-0.2.0.dist-info/top_level.txt
kingdom_core-0.2.0.dist-info/RECORD
